{
  "creation_block": 24503886,
  "last_scanned_block": 24583804,
  "events": [
    {
      "event": "RoleGranted",
      "blockNumber": 24503886,
      "transactionIndex": 33,
      "logIndex": 98,
      "args": {
        "roleId": 0,
        "account": "0xcd05909C4A1F8E501e4ED554cEF4Ed5E48D9b852",
        "delay": 0,
        "since": 1771660595,
        "newMember": true
      }
    },
    {
      "event": "RoleRevoked",
      "blockNumber": 24503886,
      "transactionIndex": 33,
      "logIndex": 143,
      "args": {
        "roleId": 0,
        "account": "0xcd05909C4A1F8E501e4ED554cEF4Ed5E48D9b852"
      }
    },
    {
      "event": "RoleGranted",
      "blockNumber": 24503886,
      "transactionIndex": 33,
      "logIndex": 384,
      "args": {
        "roleId": 601,
        "account": "0x33A72Bd7EC2f44de7f45123765664B4a1f280E84",
        "delay": 0,
        "since": 1771660595,
        "newMember": true
      }
    },
    {
      "event": "RoleGranted",
      "blockNumber": 24503886,
      "transactionIndex": 33,
      "logIndex": 385,
      "args": {
        "roleId": 4,
        "account": "0xF6a9bd8F6DC537675D499Ac1CA14f2c55d8b5569",
        "delay": 0,
        "since": 1771660595,
        "newMember": true
      }
    },
    {
      "event": "RoleGranted",
      "blockNumber": 24503886,
      "transactionIndex": 33,
      "logIndex": 386,
      "args": {
        "roleId": 1,
        "account": "0xA045A070FbA96042e7333b9c397E0dD9f5160D7e",
        "delay": 0,
        "since": 1771660595,
        "newMember": true
      }
    },
    {
      "event": "RoleGranted",
      "blockNumber": 24503886,
      "transactionIndex": 33,
      "logIndex": 387,
      "args": {
        "roleId": 1000,
        "account": "0xa1c0E2ce1556ad604A7F5E10feAF49c16860d65B",
        "delay": 0,
        "since": 1771660595,
        "newMember": true
      }
    },
    {
      "event": "RoleGranted",
      "blockNumber": 24503886,
      "transactionIndex": 33,
      "logIndex": 388,
      "args": {
        "roleId": 3,
        "account": "0xa1c0E2ce1556ad604A7F5E10feAF49c16860d65B",
        "delay": 0,
        "since": 1771660595,
        "newMember": true
      }
    },
    {
      "event": "RoleGranted",
      "blockNumber": 24503886,
      "transactionIndex": 33,
      "logIndex": 389,
      "args": {
        "roleId": 500,
        "account": "0x5090e3657e5E39233bE92EA4ce08a1f3489eF46E",
        "delay": 0,
        "since": 1771660595,
        "newMember": true
      }
    },
    {
      "event": "RoleGranted",
      "blockNumber": 24503886,
      "transactionIndex": 33,
      "logIndex": 390,
      "args": {
        "roleId": 400,
        "account": "0x5090e3657e5E39233bE92EA4ce08a1f3489eF46E",
        "delay": 0,
        "since": 1771660595,
        "newMember": true
      }
    },
    {
      "event": "RoleGranted",
      "blockNumber": 24503886,
      "transactionIndex": 33,
      "logIndex": 391,
      "args": {
        "roleId": 7,
        "account": "0x5090e3657e5E39233bE92EA4ce08a1f3489eF46E",
        "delay": 0,
        "since": 1771660595,
        "newMember": true
      }
    },
    {
      "event": "RoleGranted",
      "blockNumber": 24503886,
      "transactionIndex": 33,
      "logIndex": 392,
      "args": {
        "roleId": 5,
        "account": "0x5E79A980bca10B7EdE603E2dD69E1303c5F851D8",
        "delay": 0,
        "since": 1771660595,
        "newMember": true
      }
    },
    {
      "event": "RoleGranted",
      "blockNumber": 24503886,
      "transactionIndex": 33,
      "logIndex": 393,
      "args": {
        "roleId": 6,
        "account": "0x2C0DB639899f94a420e3706750F5541dc713433e",
        "delay": 0,
        "since": 1771660595,
        "newMember": true
      }
    },
    {
      "event": "RoleGranted",
      "blockNumber": 24504000,
      "transactionIndex": 149,
      "logIndex": 411,
      "args": {
        "roleId": 100,
        "account": "0x81Bd70230a9D0928095364E3E72a900727e4Af6e",
        "delay": 0,
        "since": 1771661963,
        "newMember": true
      }
    }
  ]
}